{"chunk_definitions":[{"row":29,"row_count":1,"visible":true,"expansion_state":0,"options":{"engine":"r","label":"paquetes","warning":false,"message":false},"document_id":"4D8569F9","chunk_id":"csm7doduvzz1l","chunk_label":"paquetes"},{"row":44,"row_count":1,"visible":true,"expansion_state":0,"options":{"engine":"r","label":"unnamed-chunk-424"},"document_id":"4D8569F9","chunk_id":"chzmtydaipjcu","chunk_label":"unnamed-chunk-1"},{"row":53,"row_count":1,"visible":true,"expansion_state":0,"options":{"engine":"r","label":"unnamed-chunk-438"},"document_id":"4D8569F9","chunk_id":"c8lyfd4k9enf5","chunk_label":"unnamed-chunk-2"},{"row":68,"row_count":1,"visible":true,"expansion_state":0,"options":{"engine":"r","warning":false,"message":false,"label":"unnamed-chunk-426"},"document_id":"4D8569F9","chunk_id":"cyq9o231mz884","chunk_label":"unnamed-chunk-3"},{"row":74,"row_count":1,"visible":true,"expansion_state":0,"options":{"engine":"r","label":"unnamed-chunk-432"},"document_id":"4D8569F9","chunk_id":"czvu7wownymh6","chunk_label":"unnamed-chunk-4"},{"row":78,"row_count":1,"visible":true,"expansion_state":0,"options":{"engine":"r","label":"unnamed-chunk-433"},"document_id":"4D8569F9","chunk_id":"c3kxjyn3af2w5","chunk_label":"unnamed-chunk-5"},{"row":82,"row_count":1,"visible":true,"expansion_state":0,"options":{"engine":"r","label":"unnamed-chunk-434"},"document_id":"4D8569F9","chunk_id":"cpst0x92fmkw9","chunk_label":"unnamed-chunk-6"},{"row":87,"row_count":1,"visible":true,"expansion_state":0,"options":{"engine":"r","label":"unnamed-chunk-435"},"document_id":"4D8569F9","chunk_id":"chge1rg4rb67o","chunk_label":"unnamed-chunk-7"},{"row":109,"row_count":1,"visible":true,"expansion_state":0,"options":{"engine":"r","label":"unnamed-chunk-442"},"document_id":"4D8569F9","chunk_id":"c8lbvy5p4w6vj","chunk_label":"unnamed-chunk-8"}],"doc_write_time":1668040239,"chunk_rendered_width":700}